[{"name": "1st Beach (Eastons Beach)", "url": "/1st-Beach-Eastons-Beach-Surf-Report/907/", "country": {"iso": "us"}, "region": {"_id": 21}, "lon": -71.2906, "hasNetcam": false, "lat": 41.4867, "_id": 907, "description": ""}, {"name": "2nd Beach (Sachuest Beach)", "url": "/2nd-Beach-Sachuest-Beach-Surf-Report/846/", "country": {"iso": "us"}, "region": {"_id": 21}, "lon": -71.257, "hasNetcam": false, "lat": 41.4871, "_id": 846, "description": ""}, {"name": "Abels Hill", "url": "/Abels-Hill-Surf-Report/978/", "country": {"iso": "us"}, "region": {"_id": 21}, "lon": -70.7076, "hasNetcam": false, "lat": 41.3422, "_id": 978, "description": ""}, {"name": "Baileys Beach", "url": "/Baileys-Beach-Surf-Report/2096/", "country": {"iso": "us"}, "region": {"_id": 21}, "lon": -71.313, "hasNetcam": false, "lat": 41.4557, "_id": 2096, "description": ""}, {"name": "Block Island", "url": "/Block-Island-Surf-Report/4057/", "country": {"iso": "us"}, "region": {"_id": 21}, "lon": -71.5783, "hasNetcam": false, "lat": 41.1463, "_id": 4057, "description": " "}, {"name": "Breachway", "url": "/Breachway-Surf-Report/784/", "country": {"iso": "us"}, "region": {"_id": 21}, "lon": -71.6393, "hasNetcam": false, "lat": 41.3541, "_id": 784, "description": ""}, {"name": "Cape Ann", "url": "/Cape-Ann-Surf-Report/370/", "country": {"iso": "us"}, "region": {"_id": 21}, "lon": -70.617, "hasNetcam": false, "lat": 42.6276, "_id": 370, "description": ""}, {"name": "Cape Cod", "url": "/Cape-Cod-Surf-Report/373/", "country": {"iso": "us"}, "region": {"_id": 21}, "lon": -69.963, "hasNetcam": false, "lat": 41.9003, "_id": 373, "description": "Covering all the breaks on Cape Cod National Seashore"}, {"name": "Costellos", "url": "/Costellos-Surf-Report/2077/", "country": {"iso": "us"}, "region": {"_id": 21}, "lon": -70.7747, "hasNetcam": false, "lat": 42.956, "_id": 2077, "description": ""}, {"name": "East Beach", "url": "/East-Beach-Surf-Report/4059/", "country": {"iso": "us"}, "region": {"_id": 21}, "lon": -71.681, "hasNetcam": false, "lat": 41.3447, "_id": 4059, "description": " "}, {"name": "Elbow Ledge", "url": "/Elbow-Ledge-Surf-Report/574/", "country": {"iso": "us"}, "region": {"_id": 21}, "lon": -71.31, "hasNetcam": false, "lat": 41.42, "_id": 574, "description": ""}, {"name": "Fortunes Rocks", "url": "/Fortunes-Rocks-Surf-Report/363/", "country": {"iso": "us"}, "region": {"_id": 21}, "lon": -70.3517, "hasNetcam": false, "lat": 43.44, "_id": 363, "description": ""}, {"name": "Green Harbor", "url": "/Green-Harbor-Surf-Report/864/", "country": {"iso": "us"}, "region": {"_id": 21}, "lon": -70.645, "hasNetcam": false, "lat": 42.0757, "_id": 864, "description": ""}, {"name": "Hampton Beach", "url": "/Hampton-Beach-Surf-Report/2074/", "country": {"iso": "us"}, "region": {"_id": 21}, "lon": -70.8052, "hasNetcam": false, "lat": 42.9133, "_id": 2074, "description": ""}, {"name": "Higgins Beach", "url": "/Higgins-Beach-Surf-Report/362/", "country": {"iso": "us"}, "region": {"_id": 21}, "lon": -70.2751, "hasNetcam": false, "lat": 43.5575, "_id": 362, "description": ""}, {"name": "Jenness Beach", "url": "/Jenness-Beach-Surf-Report/881/", "country": {"iso": "us"}, "region": {"_id": 21}, "lon": -70.7595, "hasNetcam": false, "lat": 42.9857, "_id": 881, "description": ""}, {"name": "K38/39", "url": "/K38-39-Surf-Report/785/", "country": {"iso": "us"}, "region": {"_id": 21}, "lon": -71.4947, "hasNetcam": false, "lat": 41.367, "_id": 785, "description": ""}, {"name": "Kennebunk Beach", "url": "/Kennebunk-Beach-Surf-Report/364/", "country": {"iso": "us"}, "region": {"_id": 21}, "lon": -70.4819, "hasNetcam": false, "lat": 43.3464, "_id": 364, "description": ""}, {"name": "Lighthouse (Point Judith)", "url": "/Lighthouse-Point-Judith-Surf-Report/376/", "country": {"iso": "us"}, "region": {"_id": 21}, "lon": -71.4797, "hasNetcam": false, "lat": 41.3617, "_id": 376, "description": ""}, {"name": "Linkys", "url": "/Linkys-Surf-Report/2075/", "country": {"iso": "us"}, "region": {"_id": 21}, "lon": -70.769, "hasNetcam": false, "lat": 42.9638, "_id": 2075, "description": ""}, {"name": "Long Point", "url": "/Long-Point-Surf-Report/975/", "country": {"iso": "us"}, "region": {"_id": 21}, "lon": -70.6455, "hasNetcam": false, "lat": 41.3469, "_id": 975, "description": ""}, {"name": "Long Sands", "url": "/Long-Sands-Surf-Report/367/", "country": {"iso": "us"}, "region": {"_id": 21}, "lon": -70.6182, "hasNetcam": false, "lat": 43.1584, "_id": 367, "description": ""}, {"name": "Lucy Vincent", "url": "/Lucy-Vincent-Surf-Report/977/", "country": {"iso": "us"}, "region": {"_id": 21}, "lon": -70.7276, "hasNetcam": false, "lat": 41.3383, "_id": 977, "description": ""}, {"name": "Matunuck", "url": "/Matunuck-Surf-Report/377/", "country": {"iso": "us"}, "region": {"_id": 21}, "lon": -71.5393, "hasNetcam": false, "lat": 41.3714, "_id": 377, "description": ""}, {"name": "Misquamicut", "url": "/Misquamicut-Surf-Report/783/", "country": {"iso": "us"}, "region": {"_id": 21}, "lon": -71.8037, "hasNetcam": false, "lat": 41.3218, "_id": 783, "description": ""}, {"name": "Monahans Dock", "url": "/Monahans-Dock-Surf-Report/375/", "country": {"iso": "us"}, "region": {"_id": 21}, "lon": -71.4539, "hasNetcam": false, "lat": 41.4216, "_id": 375, "description": ""}, {"name": "Nahant", "url": "/Nahant-Surf-Report/1091/", "country": {"iso": "us"}, "region": {"_id": 21}, "lon": -70.9379, "hasNetcam": false, "lat": 42.442, "_id": 1091, "description": ""}, {"name": "Nantasket Beach", "url": "/Nantasket-Beach-Surf-Report/371/", "country": {"iso": "us"}, "region": {"_id": 21}, "lon": -70.8589, "hasNetcam": false, "lat": 42.2746, "_id": 371, "description": ""}, {"name": "Narragansett Beach", "url": "/Narragansett-Beach-Surf-Report/1103/", "country": {"iso": "us"}, "region": {"_id": 21}, "lon": -71.4529, "hasNetcam": false, "lat": 41.4354, "_id": 1103, "description": "One of the most popular surfing spots in Southern New England"}, {"name": "New England Hurricane", "url": "/New-England-Hurricane-Surf-Report/1095/", "country": {"iso": "us"}, "region": {"_id": 21}, "lon": -69.7961, "hasNetcam": false, "lat": 41.6524, "_id": 1095, "description": ""}, {"name": "Ogunquit River", "url": "/Ogunquit-River-Surf-Report/365/", "country": {"iso": "us"}, "region": {"_id": 21}, "lon": -70.5884, "hasNetcam": false, "lat": 43.2454, "_id": 365, "description": ""}, {"name": "Old Orchard Beach", "url": "/Old-Orchard-Beach-Surf-Report/852/", "country": {"iso": "us"}, "region": {"_id": 21}, "lon": -70.3709, "hasNetcam": false, "lat": 43.5141, "_id": 852, "description": ""}, {"name": "Plymouth Beach", "url": "/Plymouth-Beach-Surf-Report/4525/", "country": {"iso": "us"}, "region": {"_id": 21}, "lon": -70.6243, "hasNetcam": false, "lat": 41.9435, "_id": 4525, "description": ""}, {"name": "Popham Beach", "url": "/Popham-Beach-Surf-Report/3785/", "country": {"iso": "us"}, "region": {"_id": 21}, "lon": -69.8033, "hasNetcam": false, "lat": 43.7309, "_id": 3785, "description": "South facing beach, bisected by a river mouth at Popham Beach State Park. Works best on S or SSE swell with N or NNW winds.  shifting sands, multiple bars, but consistent left and right to either side of river mouth."}, {"name": "Ruggles", "url": "/Ruggles-Surf-Report/374/", "country": {"iso": "us"}, "region": {"_id": 21}, "lon": -71.2955, "hasNetcam": false, "lat": 41.4693, "_id": 374, "description": ""}, {"name": "Rye Rocks", "url": "/Rye-Rocks-Surf-Report/368/", "country": {"iso": "us"}, "region": {"_id": 21}, "lon": -70.7692, "hasNetcam": false, "lat": 42.9688, "_id": 368, "description": "Covers Jenness, Linkys and Foxhill too"}, {"name": "Salisbury", "url": "/Salisbury-Surf-Report/1130/", "country": {"iso": "us"}, "region": {"_id": 21}, "lon": -70.8149, "hasNetcam": false, "lat": 42.8421, "_id": 1130, "description": ""}, {"name": "Scarborough Beach", "url": "/Scarborough-Beach-Surf-Report/3710/", "country": {"iso": "us"}, "region": {"_id": 21}, "lon": -70.3082, "hasNetcam": false, "lat": 43.5429, "_id": 3710, "description": "Just south of Higgins beach, more hollow and noticeably faster."}, {"name": "Scituate", "url": "/Scituate-Surf-Report/372/", "country": {"iso": "us"}, "region": {"_id": 21}, "lon": -70.715, "hasNetcam": false, "lat": 42.1886, "_id": 372, "description": "Includes everything from Scituate to Marshfield"}, {"name": "Seabrook Beach", "url": "/Seabrook-Beach-Surf-Report/2078/", "country": {"iso": "us"}, "region": {"_id": 21}, "lon": -70.8115, "hasNetcam": false, "lat": 42.8876, "_id": 2078, "description": ""}, {"name": "Short Sands", "url": "/Short-Sands-Surf-Report/366/", "country": {"iso": "us"}, "region": {"_id": 21}, "lon": -70.606, "hasNetcam": false, "lat": 43.1761, "_id": 366, "description": ""}, {"name": "South Beach", "url": "/South-Beach-Surf-Report/976/", "country": {"iso": "us"}, "region": {"_id": 21}, "lon": -70.5317, "hasNetcam": false, "lat": 41.3487, "_id": 976, "description": ""}, {"name": "South Shore Beach", "url": "/South-Shore-Beach-Surf-Report/2967/", "country": {"iso": "us"}, "region": {"_id": 21}, "lon": -71.1358, "hasNetcam": false, "lat": 41.4929, "_id": 2967, "description": " "}, {"name": "Squibnocket", "url": "/Squibnocket-Surf-Report/974/", "country": {"iso": "us"}, "region": {"_id": 21}, "lon": -70.7619, "hasNetcam": false, "lat": 41.3169, "_id": 974, "description": ""}, {"name": "The Wall", "url": "/The-Wall-Surf-Report/369/", "country": {"iso": "us"}, "region": {"_id": 21}, "lon": -70.7958, "hasNetcam": false, "lat": 42.9312, "_id": 369, "description": ""}, {"name": "Weekapaug", "url": "/Weekapaug-Surf-Report/4058/", "country": {"iso": "us"}, "region": {"_id": 21}, "lon": -71.7617, "hasNetcam": false, "lat": 41.3284, "_id": 4058, "description": "Private Beach in Westerly"}, {"name": "Wells Beach", "url": "/Wells-Beach-Surf-Report/4218/", "country": {"iso": "us"}, "region": {"_id": 21}, "lon": -70.5605, "hasNetcam": false, "lat": 43.313, "_id": 4218, "description": "Left and right beach break. Works on all tides. A bit punchier on a lower tide. Holds a big swell but a long paddle out. "}]