[{"name": "BCs", "url": "/BCs-Surf-Report/2542/", "country": {"iso": "pr"}, "region": {"_id": 41}, "lon": -67.2046, "hasNetcam": false, "lat": 18.3897, "_id": 2542, "description": ""}, {"name": "Brewers Bay", "url": "/Brewers-Bay-Surf-Report/4085/", "country": {"iso": "vg"}, "region": {"_id": 41}, "lon": -64.6511, "hasNetcam": false, "lat": 18.4438, "_id": 4085, "description": "Only available on a good north swell. Then, it punches way above its weight class. The spot itself is created by the incoming swell bouncing off the Bays west wall, and refracting back to the middle of the bay, about 100 meters off shore"}, {"name": "Cane Garden Bay", "url": "/Cane-Garden-Bay-Surf-Report/480/", "country": {"iso": "vg"}, "region": {"_id": 41}, "lon": -64.6645, "hasNetcam": false, "lat": 18.4322, "_id": 480, "description": ""}, {"name": "Capoons Bay", "url": "/Capoons-Bay-Surf-Report/2224/", "country": {"iso": "vg"}, "region": {"_id": 41}, "lon": -64.6814, "hasNetcam": false, "lat": 18.3999, "_id": 2224, "description": ""}, {"name": "Cinnamon Bay", "url": "/Cinnamon-Bay-Surf-Report/4084/", "country": {"iso": "usvg"}, "region": {"_id": 41}, "lon": -64.7564, "hasNetcam": false, "lat": 18.355, "_id": 4084, "description": "Short right that breaks best at low tide on a 4-10 foot North Swell."}, {"name": "Crash Boat", "url": "/Crash-Boat-Surf-Report/451/", "country": {"iso": "pr"}, "region": {"_id": 41}, "lon": -67.1645, "hasNetcam": false, "lat": 18.4573, "_id": 451, "description": "and Gas Chambers"}, {"name": "Cupecoy", "url": "/Cupecoy-Surf-Report/484/", "country": {"iso": "ai"}, "region": {"_id": 41}, "lon": -63.1353, "hasNetcam": false, "lat": 18.0493, "_id": 484, "description": ""}, {"name": "Dunes (Puerto Rico)", "url": "/Dunes-Puerto-Rico-Surf-Report/452/", "country": {"iso": "pr"}, "region": {"_id": 41}, "lon": -67.0467, "hasNetcam": false, "lat": 18.5148, "_id": 452, "description": "Covers a collection of spots on the north-east coast of Puerto Rico"}, {"name": "Grassy Point", "url": "/Grassy-Point-Surf-Report/4668/", "country": {"iso": "usvg"}, "region": {"_id": 41}, "lon": -64.6113, "hasNetcam": false, "lat": 17.7334, "_id": 4668, "description": ""}, {"name": "Hull Bay", "url": "/Hull-Bay-Surf-Report/1260/", "country": {"iso": "usvg"}, "region": {"_id": 41}, "lon": -64.9528, "hasNetcam": false, "lat": 18.3694, "_id": 1260, "description": "Left and right coral reef"}, {"name": "Josiahs Bay", "url": "/Josiahs-Bay-Surf-Report/481/", "country": {"iso": "vg"}, "region": {"_id": 41}, "lon": -64.5904, "hasNetcam": false, "lat": 18.4473, "_id": 481, "description": ""}, {"name": "Little Malibu (Rincon)", "url": "/Little-Malibu-Rincon-Surf-Report/450/", "country": {"iso": "pr"}, "region": {"_id": 41}, "lon": -67.2613, "hasNetcam": false, "lat": 18.3437, "_id": 450, "description": ""}, {"name": "Loblolly Bay", "url": "/Loblolly-Bay-Surf-Report/482/", "country": {"iso": "vg"}, "region": {"_id": 41}, "lon": -64.3044, "hasNetcam": false, "lat": 18.7424, "_id": 482, "description": ""}, {"name": "Motones", "url": "/Motones-Surf-Report/2537/", "country": {"iso": "pr"}, "region": {"_id": 41}, "lon": -67.0666, "hasNetcam": false, "lat": 18.5146, "_id": 2537, "description": ""}, {"name": "Sandy Beach - Puerto Rico", "url": "/Sandy-Beach-Puerto-Rico-Surf-Report/2530/", "country": {"iso": "pr"}, "region": {"_id": 41}, "lon": -67.2582, "hasNetcam": false, "lat": 18.3707, "_id": 2530, "description": ""}, {"name": "Surfers Beach (Puerto Rico)", "url": "/Surfers-Beach-Puerto-Rico-Surf-Report/2544/", "country": {"iso": "pr"}, "region": {"_id": 41}, "lon": -67.1411, "hasNetcam": false, "lat": 18.5073, "_id": 2544, "description": ""}, {"name": "The Ledge", "url": "/The-Ledge-Surf-Report/485/", "country": {"iso": "ai"}, "region": {"_id": 41}, "lon": -62.8257, "hasNetcam": false, "lat": 17.9083, "_id": 485, "description": ""}, {"name": "West End", "url": "/West-End-Surf-Report/2225/", "country": {"iso": "vg"}, "region": {"_id": 41}, "lon": -64.4172, "hasNetcam": false, "lat": 18.7463, "_id": 2225, "description": ""}, {"name": "Wilderness", "url": "/Wilderness-Surf-Report/483/", "country": {"iso": "ai"}, "region": {"_id": 41}, "lon": -63.0265, "hasNetcam": false, "lat": 18.1253, "_id": 483, "description": ""}, {"name": "Wilderness (Puerto Rico)", "url": "/Wilderness-Puerto-Rico-Surf-Report/2534/", "country": {"iso": "pr"}, "region": {"_id": 41}, "lon": -67.1646, "hasNetcam": false, "lat": 18.4892, "_id": 2534, "description": ""}, {"name": "Yacht Harbour", "url": "/Yacht-Harbour-Surf-Report/4086/", "country": {"iso": "vg"}, "region": {"_id": 41}, "lon": -64.4411, "hasNetcam": false, "lat": 18.4499, "_id": 4086, "description": ""}]